fqfa/__init__.py
fqfa/py.typed
fqfa/constants/__init__.py
fqfa/constants/iupac/__init__.py
fqfa/constants/iupac/dna.py
fqfa/constants/iupac/protein.py
fqfa/constants/iupac/rna.py
fqfa/constants/translation/__init__.py
fqfa/constants/translation/table.py
fqfa/fasta/__init__.py
fqfa/fasta/fasta.py
fqfa/fastq/__init__.py
fqfa/fastq/fastq.py
fqfa/fastq/fastqread.py
fqfa/util/__init__.py
fqfa/util/file.py
fqfa/util/infer.py
fqfa/util/nucleotide.py
fqfa/util/translate.py
fqfa/validator/__init__.py
fqfa/validator/create.py
fqfa/validator/validator.py
fqfa-1.3.1.dist-info/METADATA
fqfa-1.3.1.dist-info/WHEEL
fqfa-1.3.1.dist-info/licenses/LICENSE
fqfa-1.3.1.dist-info/RECORD
