Metadata-Version: 2.1
Name: fqfa
Version: 1.3.1
Summary: A lightweight Python library for handling FASTQ and FASTA files.
Project-URL: repository, https://github.com/CountESS-Project/fqfa
Project-URL: documentation, https://fqfa.readthedocs.io/
Author-email: Alan F Rubin <alan.rubin@wehi.edu.au>
License-Expression: BSD-3-Clause
License-File: LICENSE
Classifier: Development Status :: 5 - Production/Stable
Classifier: Intended Audience :: Science/Research
Classifier: License :: OSI Approved :: BSD License
Classifier: Operating System :: OS Independent
Classifier: Programming Language :: Python :: 3
Classifier: Topic :: Scientific/Engineering :: Bio-Informatics
Requires-Python: >=3.6
Requires-Dist: dataclasses; python_version < '3.7'
Provides-Extra: dev
Requires-Dist: black; extra == 'dev'
Requires-Dist: flake8; extra == 'dev'
Requires-Dist: flake8-pyproject; extra == 'dev'
Requires-Dist: mypy; extra == 'dev'
Requires-Dist: pre-commit; extra == 'dev'
Requires-Dist: pytest; extra == 'dev'
